richillcapital_shared_kernel/DomainEvent.py
richillcapital_shared_kernel/Entity.py
richillcapital_shared_kernel/Error.py
richillcapital_shared_kernel/ValueObject.py
richillcapital_shared_kernel/__init__.py
richillcapital_shared_kernel/monads/ErrorOr.py
richillcapital_shared_kernel/monads/Maybe.py
richillcapital_shared_kernel/monads/Result.py
richillcapital_shared_kernel/monads/ResultT.py
richillcapital_shared_kernel/monads/__init__.py
richillcapital_shared_kernel-1.0.2.dist-info/METADATA
richillcapital_shared_kernel-1.0.2.dist-info/WHEEL
richillcapital_shared_kernel-1.0.2.dist-info/licenses/LICENSE
richillcapital_shared_kernel-1.0.2.dist-info/RECORD
