Metadata-Version: 2.3
Name: richillcapital-shared-kernel
Version: 1.0.2
Summary: Shared kernel
Author-email: Mengsyue Amao Tsai <mengsyue.tsai@outlook.com>
License:                     GNU GENERAL PUBLIC LICENSE
Requires-Python: >=3.12
